tqecd/__init__.py
tqecd/boundary.py
tqecd/boundary_test.py
tqecd/construction.py
tqecd/construction_test.py
tqecd/exceptions.py
tqecd/flow.py
tqecd/fragment.py
tqecd/fragment_test.py
tqecd/match.py
tqecd/measurement.py
tqecd/measurement_test.py
tqecd/pauli.py
tqecd/pauli_test.py
tqecd/predicates.py
tqecd/py.typed
tqecd/utils.py
tqecd/utils_test.py
tqecd/match_utils/__init__.py
tqecd/match_utils/cover.py
tqecd/match_utils/cover_test.py
tqecd/match_utils/sat.py
tqecd-0.1.3.dist-info/licenses/LICENSE
tqecd-0.1.3.dist-info/METADATA
tqecd-0.1.3.dist-info/WHEEL
tqecd-0.1.3.dist-info/top_level.txt
tqecd-0.1.3.dist-info/RECORD
