Metadata-Version: 2.4
Name: tqecd
Version: 0.1.3
Summary: Automatically find detectors in a topologically quantum error corrected computation
Author-email: TQEC community <tqec-design-automation@googlegroups.com>
License:                                  Apache License
Project-URL: Documentation, https://tqec.github.io/tqecd/
Project-URL: Repository, https://github.com/tqec/tqecd
Project-URL: Issues, https://github.com/tqec/tqecd/issues
Keywords: topological quantum error correction,qec,detectors
Classifier: Development Status :: 4 - Beta
Classifier: Intended Audience :: Developers
Classifier: Intended Audience :: Science/Research
Classifier: License :: OSI Approved :: Apache Software License
Classifier: Natural Language :: English
Classifier: Operating System :: Microsoft :: Windows
Classifier: Operating System :: MacOS
Classifier: Operating System :: POSIX :: Linux
Classifier: Programming Language :: JavaScript
Classifier: Programming Language :: Python :: 3 :: Only
Classifier: Programming Language :: Python :: 3.10
Classifier: Programming Language :: Python :: 3.11
Classifier: Programming Language :: Python :: 3.12
Classifier: Programming Language :: Python :: 3.13
Classifier: Topic :: Scientific/Engineering
Classifier: Topic :: Software Development :: Libraries
Classifier: Topic :: Utilities
Classifier: Typing :: Typed
Requires-Python: >=3.9
License-File: LICENSE
Requires-Dist: numpy
Requires-Dist: stim
Requires-Dist: pycryptosat!=5.11.23
Requires-Dist: python-sat[cryptosat]
Provides-Extra: doc
Requires-Dist: sphinx<=8.1.3; extra == "doc"
Requires-Dist: myst-parser<=4.0.1; extra == "doc"
Requires-Dist: pydata-sphinx-theme<=0.16.1; extra == "doc"
Requires-Dist: nbsphinx<=0.9.7; extra == "doc"
Requires-Dist: pandoc<=2.4; extra == "doc"
Requires-Dist: jupyter<=1.1.1; extra == "doc"
Provides-Extra: test
Requires-Dist: pytest<=8.4.1; extra == "test"
Requires-Dist: mypy<=1.18.1; extra == "test"
Requires-Dist: pytest-cov<=7.0.0; extra == "test"
Provides-Extra: bench
Requires-Dist: pyinstrument<=5.1.1; extra == "bench"
Provides-Extra: dev
Requires-Dist: pre-commit<=4.2.0; extra == "dev"
Requires-Dist: tqecd[bench,doc,test]; extra == "dev"
Requires-Dist: ruff<=0.14.2; extra == "dev"
Provides-Extra: all
Requires-Dist: tqecd[bench,dev,doc,test]; extra == "all"
Dynamic: license-file
